{"GOATUSDT": 1, "SAFEUSDT": 1, "HIVEUSDT": 2, "SANDUSDT": 1, "SWARMSUSDT": 1, "AIUSDT": 1, "DFUSDT": 1, "GRIFFAINUSDT": 2, "POPCATUSDT": 1, "ARKUSDT": 3, "SPXUSDT": 2, "AI16ZUSDT": 2, "WLDUSDT": 1, "AIXBTUSDT": 2, "ONGUSDT": 1, "DEGENUSDT": 1, "1000WHYUSDT": 1, "BANANAUSDT": 1, "STMXUSDT": 1, "WAXPUSDT": 1, "1000000MOGUSDT": 1, "SXPUSDT": 1, "MOVEUSDT": 1, "RENDERUSDT": 1, "GUSDT": 1, "AKTUSDT": 1, "MAGICUSDT": 1, "AERGOUSDT": 1, "ACTUSDT": 1, "CETUSUSDT": 2, "CHILLGUYUSDT": 1, "LUNA2USDT": 1, "COOKIEUSDT": 1, "STEEMUSDT": 2, "GASUSDT": 2, "STGUSDT": 2, "PENGUUSDT": 1, "LSKUSDT": 1, "SYNUSDT": 1, "MTLUSDT": 1, "IOSTUSDT": 1, "OMNIUSDT": 1, "SONICUSDT": 1}