{"HUMAUSDT": ["H"], "ZILUSDT": ["H", "L"], "BTCUSDT_251226": ["H"], "NEARUSDT": ["H", "L"], "LINKUSDT": ["H"], "REDUSDT": ["L"], "KAIAUSDT": ["L"], "COWUSDT": ["H"], "RPLUSDT": ["H"], "ATHUSDT": ["H", "L"], "INJUSDT": ["H", "H"], "IOTXUSDT": ["L"], "APTUSDT": ["L"], "WLDUSDT": ["H"], "ICPUSDT": ["H", "L", "H"], "NMRUSDT": ["H", "H"], "METISUSDT": ["H"], "BDXNUSDT": ["H"], "ADAUSDT": ["H"], "SPKUSDT": ["L"], "VOXELUSDT": ["H"], "CYBERUSDT": ["H"], "TRUUSDT": ["H"], "1000FLOKIUSDT": ["H"], "GUNUSDT": ["H"], "USUALUSDT": ["L"], "MASKUSDT": ["H"], "TSTUSDT": ["H"], "AIUSDT": ["L"], "TRXUSDT": ["H", "L", "L", "L"], "KNCUSDT": ["H"], "ARCUSDT": ["L"], "TAOUSDT": ["H"], "PROMPTUSDT": ["L"], "SOPHUSDT": ["H"], "ETCUSDT": ["H", "H", "H"], "NILUSDT": ["H"], "SXPUSDT": ["H", "H", "L"], "ZEREBROUSDT": ["H", "L"], "SANDUSDT": ["H", "H"], "SIRENUSDT": ["L"], "NOTUSDT": ["H", "L"], "XAIUSDT": ["L"], "SNXUSDT": ["H"], "KSMUSDT": ["H"], "NEOUSDT": ["H"], "ROSEUSDT": ["H", "L"], "BNBUSDT": ["H", "H"], "NKNUSDT": ["H"], "ZRXUSDT": ["H", "H"], "1000PEPEUSDT": ["H"], "ORDIUSDT": ["H", "L"], "BRUSDT": ["H", "L", "H", "L", "H", "L"], "PAXGUSDT": ["H", "L", "H"], "TONUSDT": ["H", "H"], "PENDLEUSDT": ["H", "L"], "OMUSDT": ["H"], "UNIUSDT": ["L"], "1000000MOGUSDT": ["H"], "TRUMPUSDT": ["H"], "OPUSDT": ["H"], "ONEUSDT": ["H"], "SPELLUSDT": ["H"], "TIAUSDT": ["H"], "LDOUSDT": ["H", "H"], "ENSUSDT": ["H"], "MYROUSDT": ["L"], "API3USDT": ["H", "L"], "ALTUSDT": ["H"], "IMXUSDT": ["H"], "ACHUSDT": ["H", "H", "L"], "POLUSDT": ["H"], "EIGENUSDT": ["H"], "WCTUSDT": ["H", "L"], "BTCUSDT_250926": ["H", "L", "H"], "HYPERUSDT": ["H"], "QTUMUSDT": ["H"], "USDCUSDT": ["H", "L", "H", "L", "H", "L", "H", "L", "H", "L"], "CFXUSDT": ["H"], "TUSDT": ["H", "L"], "BMTUSDT": ["L"], "ARBUSDT": ["H"], "BATUSDT": ["H"], "SYRUPUSDT": ["H"], "MORPHOUSDT": ["H", "H"], "1000LUNCUSDT": ["H", "H"], "FIDAUSDT": ["L"], "WIFUSDT": ["L"], "BTCUSDT": ["H", "H", "L", "H"], "COMPUSDT": ["H", "L"], "AIXBTUSDT": ["H"], "THEUSDT": ["H"], "BANDUSDT": ["H"], "AUSDT": ["H", "H", "H"], "CRVUSDT": ["H"], "LPTUSDT": ["L"], "SHELLUSDT": ["L"], "BROCCOLIF3BUSDT": ["L"], "1000SHIBUSDT": ["H"], "BERAUSDT": ["H"], "HOOKUSDT": ["H"], "PARTIUSDT": ["H"], "1000BONKUSDT": ["H"], "PIPPINUSDT": ["H"], "DYDXUSDT": ["H"], "BLURUSDT": ["L", "H"], "XTZUSDT": ["H", "H", "L"], "ALCHUSDT": ["L", "L"], "SXTUSDT": ["H"], "YFIUSDT": ["L"], "CHESSUSDT": ["L"], "MINAUSDT": ["L"], "AAVEUSDT": ["L"], "LEVERUSDT": ["L"], "VINEUSDT": ["L"], "DOTUSDT": ["L"], "STOUSDT": ["H", "L"], "KDAUSDT": ["H"], "RAREUSDT": ["L"], "RENDERUSDT": ["L", "H"], "SKATEUSDT": ["H"], "EGLDUSDT": ["H"], "CTKUSDT": ["L"], "MOODENGUSDT": ["L"], "TRBUSDT": ["H"], "TURBOUSDT": ["L"]}